MANIFEST.in
README.rst
setup.cfg
setup.py
ckanext/__init__.py
ckanext/syndicate/__init__.py
ckanext/syndicate/celery_import.py
ckanext/syndicate/plugin.py
ckanext/syndicate/tasks.py
ckanext/syndicate/tests/__init__.py
ckanext/syndicate/tests/helpers.py
ckanext/syndicate/tests/test_plugin.py
ckanext/syndicate/tests/test_tasks.py
ckanext_syndicate.egg-info/PKG-INFO
ckanext_syndicate.egg-info/SOURCES.txt
ckanext_syndicate.egg-info/dependency_links.txt
ckanext_syndicate.egg-info/entry_points.txt
ckanext_syndicate.egg-info/pbr.json
ckanext_syndicate.egg-info/requires.txt
ckanext_syndicate.egg-info/top_level.txt