Metadata-Version: 1.1
Name: ckanext-syndicate
Version: 1.0.1
Summary: Allows syndication (pushing) of datasets to another repository
Home-page: https://github.com/aptivate/ckanext-syndicate
Author: Aptivate
Author-email: info@aptivate.org
License: AGPL
Keywords: CKAN syndication replication
Platform: UNKNOWN
Classifier: Development Status :: 4 - Beta
Classifier: License :: OSI Approved :: GNU Affero General Public License v3 or later (AGPLv3+)
Classifier: Programming Language :: Python :: 2.6
Classifier: Programming Language :: Python :: 2.7
